click_schema_config/__init__.py
click_schema_config/click.py
click_schema_config/commands/codegen.py
click_schema_config/commands/templates/__init__.py.jinja
click_schema_config/commands/templates/dataclass.py.jinja
click_schema_config/py.typed
click_schema_config/read_config.py
click_schema_config/types.py
click_schema_config-0.2.5.dist-info/LICENSE
click_schema_config-0.2.5.dist-info/METADATA
click_schema_config-0.2.5.dist-info/WHEEL
click_schema_config-0.2.5.dist-info/entry_points.txt
click_schema_config-0.2.5.dist-info/RECORD
