Metadata-Version: 2.1
Name: click-schema-config
Version: 0.2.5
Summary: 
Author: Joy Void Joy
Author-email: joy.void.joy@gmail.com
Requires-Python: >=3.10,<4.0
Classifier: Programming Language :: Python :: 3
Classifier: Programming Language :: Python :: 3.10
Classifier: Programming Language :: Python :: 3.11
Requires-Dist: click (>=8.1.4,<9.0.0)
Requires-Dist: halo (>=0.0.31,<0.0.32)
Requires-Dist: jinja2 (>=3.1.2,<4.0.0)
Requires-Dist: pydantic (>=2.0.2,<3.0.0)
Requires-Dist: pyyaml (>=6.0,<7.0)
Requires-Dist: types-click (>=7.1.8,<8.0.0)
